scProject/__init__.py
scProject/matcher.py
scProject/rg.py
scProject/stats.py
scProject/viz.py
scProject-1.1.4.dist-info/LICENSE
scProject-1.1.4.dist-info/METADATA
scProject-1.1.4.dist-info/WHEEL
scProject-1.1.4.dist-info/top_level.txt
scProject-1.1.4.dist-info/RECORD
